{
  "full_name": "Reda Lahlou",
  "email": "reda.lahlou@gmail.com",
  "phone": "+212 668 521 332",
  "location": "Fès",
  "years_of_experience": 7,
  "linkedin": "linkedin.com/in/reda-lahlou",
  "github": "github.com/reda56",
  "roles_held": [
    "DevOps Engineer",
    "SRE Engineer"
  ],
  "programming_languages": [
    "Go",
    "YAML",
    "Bash"
  ],
  "technical_skills": [
    "Linux",
    "Prometheus",
    "Azure",
    "ELK Stack",
    "Docker",
    "Kubernetes"
  ],
  "spoken_languages": [
    "Arabe",
    "Français"
  ],
  "certifications": [],
  "seniority_technologies": [
    {
      "technology": "Linux",
      "level": "Senior"
    },
    {
      "technology": "Prometheus",
      "level": "Senior"
    },
    {
      "technology": "Azure",
      "level": "Senior"
    }
  ],
  "seniority_programming_languages": [
    {
      "language": "Go",
      "level": "Senior"
    },
    {
      "language": "YAML",
      "level": "Senior"
    }
  ],
  "industry": {
    "primary_industries": [
      "Énergie",
      "Manufacturing",
      "Santé"
    ]
  },
  "summary": "7 ans d'expérience en tant que DevOps Engineer. Compétences avancées en Linux, Prometheus, Azure. Rigoureux, autonome et orienté résultats. Expérience dans des environnements Agile/Scrum.",
  "education_level": "Bac + 3",
  "field_of_studies": "Big Data",
  "work_experience": "Chez CIH Bank (2019-2021), j'ai travaillé en tant que DevOps Engineer en utilisant Ansible, Azure, AWS et HCL. Chez CIH Bank (2021-2022), j'ai travaillé en tant que DevOps Engineer en utilisant AWS, Jenkins, Bash, Docker, ArgoCD et Bash. Chez OCP (2022-2026), j'ai travaillé en tant que DevOps Engineer en utilisant Azure, Helm, Grafana, Terraform, Jenkins et Python, YAML.",
  "projects": "Projet 'Cluster Kubernetes haute disponibilité' dans le secteur Santé en utilisant Terraform, GCP, Linux. Projet 'Pipeline CI/CD automatisé' dans le secteur Santé en utilisant Docker, Grafana, Helm. Projet 'Migration infrastructure vers le Cloud' dans le secteur Santé en utilisant GitLab CI/CD, Helm, ArgoCD.",
  "file_path": "synthetic_cvs/cv_0185_reda_lahlou.json",
  "parsing_confidence": 0.76,
  "experience_timeline": [
    {
      "year_start": 2019,
      "year_end": 2021,
      "company": "CIH Bank",
      "skills_acquired": [
        "Ansible",
        "Azure",
        "AWS"
      ],
      "languages_used": [
        "HCL"
      ]
    },
    {
      "year_start": 2021,
      "year_end": 2022,
      "company": "CIH Bank",
      "skills_acquired": [
        "AWS",
        "Jenkins",
        "Bash",
        "Docker",
        "ArgoCD"
      ],
      "languages_used": [
        "Bash"
      ]
    },
    {
      "year_start": 2022,
      "year_end": 2026,
      "company": "OCP",
      "skills_acquired": [
        "Azure",
        "Helm",
        "Grafana",
        "Terraform",
        "Jenkins"
      ],
      "languages_used": [
        "Python",
        "YAML"
      ]
    }
  ],
  "universite": "FST Mohammedia",
  "seniority_level_global": "Senior"
}